aiocircuitbreaker/__init__.py
aiocircuitbreaker/aiocircuitbreaker.py
aiocircuitbreaker-2.0.0.dist-info/LICENSE
aiocircuitbreaker-2.0.0.dist-info/WHEEL
aiocircuitbreaker-2.0.0.dist-info/METADATA
aiocircuitbreaker-2.0.0.dist-info/RECORD
