Metadata-Version: 2.1
Name: aiocircuitbreaker
Version: 2.0.0
Summary: This is an async Python implementation of the circuitbreaker library https://github.com/fabfuel/circuitbreaker.
Home-page: https://github.com/GenyaSol/aiocircuitbreaker
Author: Evgeny Solomatin
Author-email: solgenya@gmail.com
Requires-Python: >=3.9.0,<4.0.0
Classifier: Programming Language :: Python :: 3
Classifier: Programming Language :: Python :: 3.10
Classifier: Programming Language :: Python :: 3.9
Project-URL: Repository, https://github.com/GenyaSol/aiocircuitbreaker
